{"tags":{},"filePath":"/Users/eelco/Development/appulse/saas-ui/packages/saas-ui-layout/src/index.ts","description":"","displayName":"EmptyStateBody","methods":[],"props":{"spacing":{"defaultValue":null,"description":"","name":"spacing","parent":{"fileName":"saas-ui/packages/saas-ui-layout/src/empty-state.tsx","name":"EmptyStateBodyProps"},"declarations":[{"fileName":"saas-ui/packages/saas-ui-layout/src/empty-state.tsx","name":"EmptyStateBodyProps"}],"required":false,"type":{"name":"ResponsiveValue<Union<number | \"px\" | (string & {}) | \"inherit\" | \"-moz-initial\" | \"initial\" | \"revert\" | \"revert-layer\" | \"unset\" | \"auto\" | \"1\" | \"-1\" | \"2\" | \"-2\" | \"3\" | \"-3\" | \"4\" | \"-4\" | \"5\" | ... 55 more ... | \"-3.5\">>"}}}}